{
	"users": [{
			"id": 0,
			"name": "Talley Mcpherson"
		},
		{
			"id": 1,
			"name": "Raquel Acevedo"
		},
		{
			"id": 2,
			"name": "Rosalie Finley"
		},
		{
			"id": 3,
			"name": "Ivy Alvarez"
		},
		{
			"id": 4,
			"name": "Riddle Carpenter"
		},
		{
			"id": 5,
			"name": "Nikki Schroeder"
		},
		{
			"id": 6,
			"name": "Mcclure Johnson"
		},
		{
			"id": 7,
			"name": "Ware Montoya"
		},
		{
			"id": 8,
			"name": "Snow Ewing"
		},
		{
			"id": 9,
			"name": "Guthrie William"
		},
		{
			"id": 10,
			"name": "Cornelia Tyson"
		},
		{
			"id": 11,
			"name": "Glenda Bridges"
		},
		{
			"id": 12,
			"name": "Newton Baxter"
		},
		{
			"id": 13,
			"name": "Yesenia Guy"
		},
		{
			"id": 14,
			"name": "Evangeline Jordan"
		},
		{
			"id": 15,
			"name": "Blankenship Prince"
		},
		{
			"id": 16,
			"name": "Wagner Gardner"
		},
		{
			"id": 17,
			"name": "Sadie Gay"
		},
		{
			"id": 18,
			"name": "Hull Jenkins"
		},
		{
			"id": 19,
			"name": "Lester Armstrong"
		}
	],
	"projects": [{
			"id": 0,
			"project": "Tribalog",
			"company": "RODEOMAD"
		},
		{
			"id": 1,
			"project": "Playce",
			"company": "PULZE"
		},
		{
			"id": 2,
			"project": "Artworlds",
			"company": "PANZENT"
		},
		{
			"id": 3,
			"project": "Kiosk",
			"company": "STELAECOR"
		},
		{
			"id": 4,
			"project": "Geostele",
			"company": "ENORMO"
		},
		{
			"id": 5,
			"project": "Dancerity",
			"company": "CAPSCREEN"
		},
		{
			"id": 6,
			"project": "Kaggle",
			"company": "IMPERIUM"
		},
		{
			"id": 7,
			"project": "Kenegy",
			"company": "SONGBIRD"
		},
		{
			"id": 8,
			"project": "Strozen",
			"company": "ZILLAN"
		},
		{
			"id": 9,
			"project": "Cormoran",
			"company": "VIRXO"
		},
		{
			"id": 10,
			"project": "Sensate",
			"company": "BUGSALL"
		},
		{
			"id": 11,
			"project": "Imaginart",
			"company": "IMANT"
		},
		{
			"id": 12,
			"project": "Baluba",
			"company": "QUILCH"
		},
		{
			"id": 13,
			"project": "Gorganic",
			"company": "LYRIA"
		},
		{
			"id": 14,
			"project": "Entogrok",
			"company": "SKINSERVE"
		},
		{
			"id": 15,
			"project": "Eargo",
			"company": "COMVENE"
		},
		{
			"id": 16,
			"project": "Quiltigen",
			"company": "SNACKTION"
		},
		{
			"id": 17,
			"project": "Nexgene",
			"company": "MICROLUXE"
		},
		{
			"id": 18,
			"project": "Enthaze",
			"company": "ULTRIMAX"
		},
		{
			"id": 19,
			"project": "Comvex",
			"company": "SCENTY"
		},
		{
			"id": 20,
			"project": "Avenetro",
			"company": "COMBOGENE"
		},
		{
			"id": 21,
			"project": "Supportal",
			"company": "TURNLING"
		},
		{
			"id": 22,
			"project": "Isosphere",
			"company": "SARASONIC"
		},
		{
			"id": 23,
			"project": "Zomboid",
			"company": "SHOPABOUT"
		},
		{
			"id": 24,
			"project": "Myopium",
			"company": "DREAMIA"
		},
		{
			"id": 25,
			"project": "Isotronic",
			"company": "CENTURIA"
		},
		{
			"id": 26,
			"project": "Zappix",
			"company": "VORATAK"
		},
		{
			"id": 27,
			"project": "Portalis",
			"company": "HYDROCOM"
		},
		{
			"id": 28,
			"project": "Wrapture",
			"company": "TSUNAMIA"
		},
		{
			"id": 29,
			"project": "Exotechno",
			"company": "EZENTIA"
		},
		{
			"id": 30,
			"project": "Musix",
			"company": "GEOFORMA"
		},
		{
			"id": 31,
			"project": "Illumity",
			"company": "PHOTOBIN"
		},
		{
			"id": 32,
			"project": "Exerta",
			"company": "SHADEASE"
		},
		{
			"id": 33,
			"project": "Quadeebo",
			"company": "QUILK"
		},
		{
			"id": 34,
			"project": "Extro",
			"company": "IPLAX"
		},
		{
			"id": 35,
			"project": "Apextri",
			"company": "VALPREAL"
		},
		{
			"id": 36,
			"project": "Talkalot",
			"company": "GLUKGLUK"
		},
		{
			"id": 37,
			"project": "Neocent",
			"company": "MARQET"
		},
		{
			"id": 38,
			"project": "Comtrak",
			"company": "PORTALINE"
		},
		{
			"id": 39,
			"project": "Xsports",
			"company": "KEGULAR"
		},
		{
			"id": 40,
			"project": "Architax",
			"company": "VERBUS"
		},
		{
			"id": 41,
			"project": "Envire",
			"company": "KAGE"
		},
		{
			"id": 42,
			"project": "Geeketron",
			"company": "TECHMANIA"
		},
		{
			"id": 43,
			"project": "Aquamate",
			"company": "NITRACYR"
		},
		{
			"id": 44,
			"project": "Plexia",
			"company": "XEREX"
		},
		{
			"id": 45,
			"project": "Endipine",
			"company": "IMMUNICS"
		},
		{
			"id": 46,
			"project": "Xinware",
			"company": "GINK"
		},
		{
			"id": 47,
			"project": "Zensus",
			"company": "EBIDCO"
		},
		{
			"id": 48,
			"project": "Menbrain",
			"company": "GEOFARM"
		},
		{
			"id": 49,
			"project": "Euron",
			"company": "MEDALERT"
		}
	],
	"po": [{
			"ponumber": "9ebbc364-0739-43f3-b0cc-501f1ae12da7",
			"id": 0,
			"projectid": 20,
			"created": "2016-03-17T05:35:03 -08:00"
		},
		{
			"ponumber": "491d78d5-4ca1-44d7-8be2-89b5ddc30cb5",
			"id": 1,
			"projectid": 18,
			"created": "2015-07-14T08:37:52 -08:00"
		},
		{
			"ponumber": "94bfa01f-ddb0-4d28-89de-e7acf88fa850",
			"id": 2,
			"projectid": 42,
			"created": "2015-05-27T10:46:26 -08:00"
		},
		{
			"ponumber": "ffb867ba-91c5-4d1d-aeb7-b5c1b21a9d0b",
			"id": 3,
			"projectid": 11,
			"created": "2017-05-31T11:04:11 -08:00"
		},
		{
			"ponumber": "6b3c011b-9da5-428f-8412-d7811f45b1a9",
			"id": 4,
			"projectid": 41,
			"created": "2016-10-20T02:22:58 -08:00"
		},
		{
			"ponumber": "ecd21daa-2bac-4cef-9cc0-99ba6108ac59",
			"id": 5,
			"projectid": 44,
			"created": "2017-11-26T01:45:19 -08:00"
		},
		{
			"ponumber": "b4f5329b-365a-4a8b-9209-e8d36ced7a39",
			"id": 6,
			"projectid": 13,
			"created": "2014-09-04T12:13:18 -08:00"
		},
		{
			"ponumber": "c2ef1a6d-6713-4d54-89ff-379ae3ed5c50",
			"id": 7,
			"projectid": 4,
			"created": "2015-06-28T06:19:29 -08:00"
		},
		{
			"ponumber": "30e8a4e6-9ff3-4394-b02b-d0c4af3b30b8",
			"id": 8,
			"projectid": 18,
			"created": "2017-05-11T08:36:52 -08:00"
		},
		{
			"ponumber": "5cc595a2-1e18-4615-8074-ac934f8c151e",
			"id": 9,
			"projectid": 12,
			"created": "2016-02-10T07:29:05 -08:00"
		},
		{
			"ponumber": "ae21795e-eb18-4e90-9423-348faaa09cd4",
			"id": 10,
			"projectid": 2,
			"created": "2014-10-15T09:54:30 -08:00"
		},
		{
			"ponumber": "ef4c1bbc-758d-4a4c-ad64-bbe5fb8437bd",
			"id": 11,
			"projectid": 15,
			"created": "2016-10-09T06:17:28 -08:00"
		},
		{
			"ponumber": "1ca58940-7ea2-4b76-af2d-a5a2bc873e42",
			"id": 12,
			"projectid": 6,
			"created": "2015-04-29T01:30:22 -08:00"
		},
		{
			"ponumber": "bca32260-9721-4ae0-a0aa-31f591dda96e",
			"id": 13,
			"projectid": 47,
			"created": "2014-04-09T04:42:25 -08:00"
		},
		{
			"ponumber": "1a820bcb-83fe-47db-9d5e-99fa1186faca",
			"id": 14,
			"projectid": 28,
			"created": "2015-02-02T06:49:38 -08:00"
		},
		{
			"ponumber": "18aad05f-9871-4848-918e-6ff8e6df0327",
			"id": 15,
			"projectid": 44,
			"created": "2017-07-06T01:53:23 -08:00"
		},
		{
			"ponumber": "89ede7a3-f5fe-4ffd-8fa8-9ea01f26e87d",
			"id": 16,
			"projectid": 28,
			"created": "2014-06-12T11:33:12 -08:00"
		},
		{
			"ponumber": "3a5da800-7672-45db-814a-2b972ff03c09",
			"id": 17,
			"projectid": 16,
			"created": "2016-03-20T02:48:53 -08:00"
		},
		{
			"ponumber": "65383935-17f9-4a3b-a5f2-aa87ce7391c7",
			"id": 18,
			"projectid": 7,
			"created": "2014-10-19T05:43:29 -08:00"
		},
		{
			"ponumber": "a6404db0-8bfc-42cc-beba-e0a5b176321d",
			"id": 19,
			"projectid": 24,
			"created": "2018-02-22T05:56:22 -08:00"
		},
		{
			"ponumber": "4c5b59e0-3764-45d1-92c2-f9433ad65ea1",
			"id": 20,
			"projectid": 13,
			"created": "2016-03-23T04:35:23 -08:00"
		},
		{
			"ponumber": "ef2914d7-40d1-46f8-809a-fd75deb4e930",
			"id": 21,
			"projectid": 32,
			"created": "2017-07-14T11:20:08 -08:00"
		},
		{
			"ponumber": "f31e29b5-619b-46e1-92f2-551377384067",
			"id": 22,
			"projectid": 48,
			"created": "2015-10-08T07:10:30 -08:00"
		},
		{
			"ponumber": "5edaff55-c5f1-46f8-9e87-19530145a1c7",
			"id": 23,
			"projectid": 28,
			"created": "2014-02-13T02:24:04 -08:00"
		},
		{
			"ponumber": "4ec84593-f958-465e-ace1-9b3c41c286e6",
			"id": 24,
			"projectid": 27,
			"created": "2015-09-20T01:16:40 -08:00"
		},
		{
			"ponumber": "8d35fbbd-18a5-4b99-abc5-c98e828e0800",
			"id": 25,
			"projectid": 25,
			"created": "2015-09-12T06:14:32 -08:00"
		},
		{
			"ponumber": "42c26bce-fa5a-4800-9866-4f0f05647f24",
			"id": 26,
			"projectid": 19,
			"created": "2016-11-07T08:51:48 -08:00"
		},
		{
			"ponumber": "0f3dde90-a477-45f2-adce-5b25955c09bc",
			"id": 27,
			"projectid": 37,
			"created": "2015-04-12T04:11:42 -08:00"
		},
		{
			"ponumber": "8b1429f6-b122-4458-b48f-ba77f36fe147",
			"id": 28,
			"projectid": 20,
			"created": "2014-03-15T11:35:35 -08:00"
		},
		{
			"ponumber": "b9b61e68-b103-48c8-b598-615db5e1a658",
			"id": 29,
			"projectid": 34,
			"created": "2016-07-06T11:15:50 -08:00"
		},
		{
			"ponumber": "b10049d6-2c59-4a2e-9ac7-e2080cfc578f",
			"id": 30,
			"projectid": 36,
			"created": "2015-03-02T08:59:46 -08:00"
		},
		{
			"ponumber": "d97aa062-be9e-4236-b6b8-acdf85d63a6f",
			"id": 31,
			"projectid": 33,
			"created": "2015-12-08T03:46:09 -08:00"
		},
		{
			"ponumber": "125a99a8-2bc8-4517-a259-a919f0f4256d",
			"id": 32,
			"projectid": 14,
			"created": "2017-01-24T01:51:18 -08:00"
		},
		{
			"ponumber": "6ff9f4ec-8b8e-4cda-b116-e5e2005e5d63",
			"id": 33,
			"projectid": 27,
			"created": "2015-10-09T02:36:52 -08:00"
		},
		{
			"ponumber": "a0730e11-64de-4794-9e04-42a60e69c90b",
			"id": 34,
			"projectid": 4,
			"created": "2014-05-04T11:25:42 -08:00"
		},
		{
			"ponumber": "d9240180-b9a8-4229-8f58-6be207677338",
			"id": 35,
			"projectid": 50,
			"created": "2015-05-27T03:15:45 -08:00"
		},
		{
			"ponumber": "dfcd2098-0615-4e69-aeaf-f23e3844785f",
			"id": 36,
			"projectid": 47,
			"created": "2016-06-07T10:56:37 -08:00"
		},
		{
			"ponumber": "66022bdc-8e78-401a-afd5-f693d95280f0",
			"id": 37,
			"projectid": 43,
			"created": "2016-10-24T04:08:02 -08:00"
		},
		{
			"ponumber": "39f77aaf-dec2-4da3-8844-382bd950aa26",
			"id": 38,
			"projectid": 31,
			"created": "2016-06-03T12:38:31 -08:00"
		},
		{
			"ponumber": "50da1b37-4d11-4df2-a300-b5617156f58e",
			"id": 39,
			"projectid": 8,
			"created": "2017-10-04T07:39:54 -08:00"
		},
		{
			"ponumber": "9f38c7ef-4bbd-48d2-adbb-04896f94339e",
			"id": 40,
			"projectid": 32,
			"created": "2014-03-20T01:32:59 -08:00"
		},
		{
			"ponumber": "d266b9b5-b8e2-4f33-a7c3-a30a3173a5f8",
			"id": 41,
			"projectid": 16,
			"created": "2016-09-15T11:45:15 -08:00"
		},
		{
			"ponumber": "244d86ba-f221-4cb9-a1bc-7c0955ae19a2",
			"id": 42,
			"projectid": 34,
			"created": "2014-01-24T10:12:37 -08:00"
		},
		{
			"ponumber": "161d5cb3-4970-442d-9b0e-6813bdf8acc9",
			"id": 43,
			"projectid": 18,
			"created": "2017-08-02T03:17:52 -08:00"
		},
		{
			"ponumber": "0b4308bc-999a-4b70-b654-44a9d3df4a6a",
			"id": 44,
			"projectid": 17,
			"created": "2014-04-12T09:35:19 -08:00"
		},
		{
			"ponumber": "61e1822b-04c2-4f85-bab9-af5ef5f38f61",
			"id": 45,
			"projectid": 3,
			"created": "2016-11-21T03:12:12 -08:00"
		},
		{
			"ponumber": "d4864e51-b9b7-4a39-bb99-c2ee0c474a58",
			"id": 46,
			"projectid": 16,
			"created": "2014-05-24T02:38:30 -08:00"
		},
		{
			"ponumber": "3b22e7f5-d971-43c5-a59b-5645bc3d2bb0",
			"id": 47,
			"projectid": 13,
			"created": "2016-05-15T11:48:20 -08:00"
		},
		{
			"ponumber": "220b5a37-1576-4607-a9d8-dd58c03e5240",
			"id": 48,
			"projectid": 44,
			"created": "2014-05-17T05:40:29 -08:00"
		},
		{
			"ponumber": "f8e2a3ad-a5ab-4012-bae1-1d7dd0bafcd2",
			"id": 49,
			"projectid": 24,
			"created": "2014-08-05T02:22:45 -08:00"
		},
		{
			"ponumber": "8d985c61-1459-42ba-bce5-9e1f1e41c917",
			"id": 50,
			"projectid": 15,
			"created": "2015-04-17T01:44:08 -08:00"
		},
		{
			"ponumber": "b067e75e-757e-40ff-a4a8-e048ace21b91",
			"id": 51,
			"projectid": 40,
			"created": "2014-12-19T03:23:44 -08:00"
		},
		{
			"ponumber": "4cc9a41c-bfbf-4c6d-8d06-2ef6450c61c7",
			"id": 52,
			"projectid": 42,
			"created": "2017-09-04T11:56:20 -08:00"
		},
		{
			"ponumber": "9b719dc3-e23b-4374-a1a6-ad36138cac95",
			"id": 53,
			"projectid": 23,
			"created": "2016-03-20T03:31:10 -08:00"
		},
		{
			"ponumber": "8ae79f10-461a-4324-9937-236b70b158b4",
			"id": 54,
			"projectid": 47,
			"created": "2016-08-17T05:41:07 -08:00"
		},
		{
			"ponumber": "374df62b-8562-442f-a91d-3e4578adaeea",
			"id": 55,
			"projectid": 13,
			"created": "2015-10-04T01:30:55 -08:00"
		},
		{
			"ponumber": "28e0725e-b403-4f6d-968a-b6cb171513c1",
			"id": 56,
			"projectid": 25,
			"created": "2017-06-12T05:27:36 -08:00"
		},
		{
			"ponumber": "9d277f6f-e3b8-4f3e-b3c2-de4bb6a5c42a",
			"id": 57,
			"projectid": 44,
			"created": "2014-08-14T05:06:29 -08:00"
		},
		{
			"ponumber": "0a7a77c3-621e-425c-8c84-92634394ccce",
			"id": 58,
			"projectid": 11,
			"created": "2015-10-18T11:05:33 -08:00"
		},
		{
			"ponumber": "714b9b58-b18c-40ad-bc73-0eda78b2f1ea",
			"id": 59,
			"projectid": 45,
			"created": "2014-08-31T06:11:39 -08:00"
		},
		{
			"ponumber": "c37f1f37-c63b-4d1f-bf25-c49a1681a1f7",
			"id": 60,
			"projectid": 48,
			"created": "2017-02-01T12:55:25 -08:00"
		},
		{
			"ponumber": "8b2c8488-35d8-4973-86df-99fe71a910ae",
			"id": 61,
			"projectid": 6,
			"created": "2017-12-26T06:54:51 -08:00"
		},
		{
			"ponumber": "c01f8203-0133-46d2-95ff-a0c4e61cac80",
			"id": 62,
			"projectid": 7,
			"created": "2017-10-11T03:48:01 -08:00"
		},
		{
			"ponumber": "a658bdb4-3881-4ee5-bb74-ec3b5e250c63",
			"id": 63,
			"projectid": 44,
			"created": "2017-01-11T09:35:02 -08:00"
		},
		{
			"ponumber": "7e92d281-0847-4701-9a48-7180c9abb587",
			"id": 64,
			"projectid": 21,
			"created": "2015-08-02T05:57:13 -08:00"
		},
		{
			"ponumber": "02ac37d5-9155-4301-8c06-a2be95d73312",
			"id": 65,
			"projectid": 13,
			"created": "2014-03-27T07:07:26 -08:00"
		},
		{
			"ponumber": "fd01b9d8-6d76-4390-8bf4-ef88fa206801",
			"id": 66,
			"projectid": 1,
			"created": "2014-11-14T06:32:32 -08:00"
		},
		{
			"ponumber": "e6a82694-00ef-4ec6-9a16-bcb59a174b6b",
			"id": 67,
			"projectid": 34,
			"created": "2015-07-27T11:40:41 -08:00"
		},
		{
			"ponumber": "db067af5-9496-4e11-989e-e778bf26bb66",
			"id": 68,
			"projectid": 20,
			"created": "2016-02-14T01:39:35 -08:00"
		},
		{
			"ponumber": "f3dbdd06-76fc-43e0-a985-1f8c704fd12e",
			"id": 69,
			"projectid": 36,
			"created": "2016-12-27T07:14:01 -08:00"
		},
		{
			"ponumber": "06b1119e-ed27-46e1-8287-4520d65b87a1",
			"id": 70,
			"projectid": 49,
			"created": "2015-05-06T01:14:25 -08:00"
		},
		{
			"ponumber": "f03c81d2-f447-4d9e-9d2f-17f00136d4c8",
			"id": 71,
			"projectid": 17,
			"created": "2014-05-17T04:11:54 -08:00"
		},
		{
			"ponumber": "77f23b89-e575-4b72-84bc-972593f418e6",
			"id": 72,
			"projectid": 49,
			"created": "2017-01-22T06:17:45 -08:00"
		},
		{
			"ponumber": "fe9fae79-8266-4684-b517-6c8083523dc1",
			"id": 73,
			"projectid": 37,
			"created": "2016-06-27T12:46:32 -08:00"
		},
		{
			"ponumber": "f1e96211-4a5c-4044-b8a1-4261260a31e9",
			"id": 74,
			"projectid": 43,
			"created": "2014-11-29T06:15:27 -08:00"
		},
		{
			"ponumber": "389cbae7-4385-4b59-9e9b-2789fd2e6a0e",
			"id": 75,
			"projectid": 25,
			"created": "2015-01-13T05:00:37 -08:00"
		},
		{
			"ponumber": "f658bebf-8294-4727-8513-ead0f7248a22",
			"id": 76,
			"projectid": 22,
			"created": "2016-11-17T03:36:46 -08:00"
		},
		{
			"ponumber": "cab3d2da-ebe8-40c5-9087-6588cf6e12ef",
			"id": 77,
			"projectid": 7,
			"created": "2015-01-30T12:01:08 -08:00"
		},
		{
			"ponumber": "9a23f2df-cb7f-438d-8bf2-2ca2bd8b53f0",
			"id": 78,
			"projectid": 5,
			"created": "2017-10-05T12:15:28 -08:00"
		},
		{
			"ponumber": "22fbb3c9-38b5-40c9-b5b3-0a9703f7b00c",
			"id": 79,
			"projectid": 9,
			"created": "2015-06-09T05:07:46 -08:00"
		},
		{
			"ponumber": "41dfd7d2-f992-4d8e-9fe4-413eb58f34a8",
			"id": 80,
			"projectid": 16,
			"created": "2014-02-27T10:51:14 -08:00"
		},
		{
			"ponumber": "4ea55fb8-7f2e-4ffa-9147-dfacead583af",
			"id": 81,
			"projectid": 7,
			"created": "2017-04-23T06:56:16 -08:00"
		},
		{
			"ponumber": "e9d1cd90-2cb6-45a5-b4fb-6ce6b0b7300e",
			"id": 82,
			"projectid": 44,
			"created": "2017-09-14T11:17:15 -08:00"
		},
		{
			"ponumber": "0f57ef56-56c7-408c-978f-b32953edd849",
			"id": 83,
			"projectid": 46,
			"created": "2016-03-01T06:22:26 -08:00"
		},
		{
			"ponumber": "8dbc8c4f-65dc-41d0-856c-de474005cdaf",
			"id": 84,
			"projectid": 44,
			"created": "2016-02-17T05:37:44 -08:00"
		},
		{
			"ponumber": "2095a372-fc78-49af-b3e0-cdd08cc591cb",
			"id": 85,
			"projectid": 19,
			"created": "2016-03-05T10:20:29 -08:00"
		},
		{
			"ponumber": "fbca51af-c400-4c23-b8a3-14bc2f5ef778",
			"id": 86,
			"projectid": 15,
			"created": "2014-05-28T02:16:31 -08:00"
		},
		{
			"ponumber": "d8021687-ed54-4167-a63c-ce066385018e",
			"id": 87,
			"projectid": 37,
			"created": "2015-10-08T09:56:46 -08:00"
		},
		{
			"ponumber": "4b99698a-0366-4660-9de3-3359c75764a0",
			"id": 88,
			"projectid": 35,
			"created": "2014-12-04T06:31:04 -08:00"
		},
		{
			"ponumber": "c9f074d6-3e1f-4e69-817c-43e8315f885d",
			"id": 89,
			"projectid": 31,
			"created": "2015-07-15T05:33:28 -08:00"
		},
		{
			"ponumber": "57e4a706-2a28-40cb-8c72-fe5ccd1f077e",
			"id": 90,
			"projectid": 28,
			"created": "2015-06-24T11:12:41 -08:00"
		},
		{
			"ponumber": "1944c044-dc71-4999-872b-ca2e33546aaf",
			"id": 91,
			"projectid": 43,
			"created": "2015-12-25T04:21:31 -08:00"
		},
		{
			"ponumber": "7ec9e417-b75e-4457-90d5-ac075d7d6aa8",
			"id": 92,
			"projectid": 39,
			"created": "2015-03-25T08:20:56 -08:00"
		},
		{
			"ponumber": "e78ef15c-7747-45d4-b463-0285948a2680",
			"id": 93,
			"projectid": 27,
			"created": "2015-06-12T06:36:02 -08:00"
		},
		{
			"ponumber": "3dacfdd9-f8ff-4172-afcf-f08dfc33a734",
			"id": 94,
			"projectid": 15,
			"created": "2015-10-25T06:12:59 -08:00"
		},
		{
			"ponumber": "f4a93b70-c1dc-4b59-bb21-afe2af666427",
			"id": 95,
			"projectid": 26,
			"created": "2017-09-13T06:33:44 -08:00"
		},
		{
			"ponumber": "9c673409-9edf-485b-9bc8-5807eeb63d88",
			"id": 96,
			"projectid": 50,
			"created": "2015-12-02T11:50:39 -08:00"
		},
		{
			"ponumber": "c64334d5-1fa6-416f-a35d-cbdc0ff55ab3",
			"id": 97,
			"projectid": 41,
			"created": "2015-11-22T08:06:37 -08:00"
		},
		{
			"ponumber": "73d6af96-76a8-44e5-b75c-e071a50b845e",
			"id": 98,
			"projectid": 23,
			"created": "2017-01-21T09:11:41 -08:00"
		},
		{
			"ponumber": "c97d9250-1a9b-40e4-bed5-373d7529f297",
			"id": 99,
			"projectid": 12,
			"created": "2014-01-08T10:14:16 -08:00"
		}
	],
	"dr": [{
			"drnumber": "7b4e5bae-bfca-4a89-a91a-8ce5a0c50b10",
			"id": 0,
			"poid": 46,
			"created": "2016-02-10T05:53:58 -08:00",
			"updated": "2015-04-14T05:00:49 -08:00",
			"synced": "2016-12-16T01:23:14 -08:00"
		},
		{
			"drnumber": "6e25dca6-a14d-4247-b64d-39fe5ef94d19",
			"id": 1,
			"poid": 41,
			"created": "2014-03-23T01:45:57 -08:00",
			"updated": "2017-09-29T06:56:18 -08:00",
			"synced": "2015-07-04T09:30:34 -08:00"
		},
		{
			"drnumber": "44eef34c-d567-4552-a758-2699be0a46c2",
			"id": 2,
			"poid": 88,
			"created": "2015-08-23T07:19:04 -08:00",
			"updated": "2016-06-10T09:24:28 -08:00",
			"synced": "2016-04-25T11:35:50 -08:00"
		},
		{
			"drnumber": "8d57ffc9-2330-41a9-a118-bf74358d32c2",
			"id": 3,
			"poid": 66,
			"created": "2016-05-31T12:05:31 -08:00",
			"updated": "2014-02-19T12:17:09 -08:00",
			"synced": "2016-12-21T01:45:27 -08:00"
		},
		{
			"drnumber": "8dcf0e8d-7c53-4758-a0aa-46dc24e5aabc",
			"id": 4,
			"poid": 77,
			"created": "2014-03-14T08:05:27 -08:00",
			"updated": "2016-04-25T03:54:24 -08:00",
			"synced": "2017-05-21T03:16:39 -08:00"
		},
		{
			"drnumber": "0f8036ab-d3c3-413b-81c7-75f44f89dcba",
			"id": 5,
			"poid": 93,
			"created": "2015-08-31T12:38:51 -08:00",
			"updated": "2017-11-01T05:23:15 -08:00",
			"synced": "2015-04-18T03:51:53 -08:00"
		},
		{
			"drnumber": "9465d12f-3dcd-4ab5-9306-7f29fa2c559c",
			"id": 6,
			"poid": 81,
			"created": "2014-06-17T12:42:22 -08:00",
			"updated": "2014-03-07T07:34:13 -08:00",
			"synced": "2017-09-20T01:48:27 -08:00"
		},
		{
			"drnumber": "2ba0d916-42f4-4024-afa9-e501e3c6fffb",
			"id": 7,
			"poid": 6,
			"created": "2016-07-04T09:54:35 -08:00",
			"updated": "2018-02-22T12:16:57 -08:00",
			"synced": "2017-05-13T06:30:36 -08:00"
		},
		{
			"drnumber": "0e9d262b-9855-4642-9053-6985dc2c06f5",
			"id": 8,
			"poid": 92,
			"created": "2015-03-19T11:38:10 -08:00",
			"updated": "2017-04-19T03:41:54 -08:00",
			"synced": "2014-01-09T01:16:24 -08:00"
		},
		{
			"drnumber": "7861bc48-6888-457a-8c43-abb4e60077e8",
			"id": 9,
			"poid": 5,
			"created": "2014-07-16T10:32:42 -08:00",
			"updated": "2015-04-09T01:41:11 -08:00",
			"synced": "2017-01-19T05:58:18 -08:00"
		},
		{
			"drnumber": "5a5ef52e-a39e-4f4d-9a41-91a16f061ea8",
			"id": 10,
			"poid": 47,
			"created": "2015-09-11T05:09:18 -08:00",
			"updated": "2016-02-27T01:08:16 -08:00",
			"synced": "2016-12-19T03:04:39 -08:00"
		},
		{
			"drnumber": "688d61c2-e5b0-432d-bb76-ec9384cc2c22",
			"id": 11,
			"poid": 51,
			"created": "2016-02-27T04:34:04 -08:00",
			"updated": "2016-02-02T07:59:22 -08:00",
			"synced": "2014-08-28T12:40:19 -08:00"
		},
		{
			"drnumber": "b8d98a00-17fd-453c-845d-82da855bb07c",
			"id": 12,
			"poid": 90,
			"created": "2017-08-31T08:45:06 -08:00",
			"updated": "2014-07-03T05:52:08 -08:00",
			"synced": "2017-10-15T11:44:34 -08:00"
		},
		{
			"drnumber": "5268af99-8f39-4e5d-96f0-13d3edb8acc2",
			"id": 13,
			"poid": 47,
			"created": "2016-06-16T03:57:39 -08:00",
			"updated": "2015-06-13T07:01:34 -08:00",
			"synced": "2015-08-16T11:36:01 -08:00"
		},
		{
			"drnumber": "242caf63-6b48-4ebf-9d65-c3cd6481556d",
			"id": 14,
			"poid": 78,
			"created": "2017-04-13T10:37:35 -08:00",
			"updated": "2017-09-14T04:55:45 -08:00",
			"synced": "2016-02-02T10:48:41 -08:00"
		},
		{
			"drnumber": "f83c30d4-9bf2-46bb-a9b8-996be3b6cb1f",
			"id": 15,
			"poid": 49,
			"created": "2016-05-23T05:42:49 -08:00",
			"updated": "2016-10-26T06:01:02 -08:00",
			"synced": "2016-05-25T01:14:02 -08:00"
		},
		{
			"drnumber": "13bcd986-aa90-4021-ad1f-269347183de3",
			"id": 16,
			"poid": 85,
			"created": "2017-07-05T02:19:18 -08:00",
			"updated": "2015-08-07T12:30:27 -08:00",
			"synced": "2015-01-01T07:13:19 -08:00"
		},
		{
			"drnumber": "09922468-32a5-4a3f-ad8f-02e3069661c0",
			"id": 17,
			"poid": 61,
			"created": "2014-10-18T09:18:45 -08:00",
			"updated": "2017-04-19T04:34:05 -08:00",
			"synced": "2017-07-31T12:43:55 -08:00"
		},
		{
			"drnumber": "92c4e244-4f41-4856-827b-13c8155ba756",
			"id": 18,
			"poid": 97,
			"created": "2018-01-04T09:45:39 -08:00",
			"updated": "2017-08-05T03:10:58 -08:00",
			"synced": "2016-10-21T02:46:51 -08:00"
		},
		{
			"drnumber": "e7f6afd8-e537-4378-be78-d4c384df5e24",
			"id": 19,
			"poid": 30,
			"created": "2016-02-12T01:44:56 -08:00",
			"updated": "2017-06-19T05:52:33 -08:00",
			"synced": "2018-03-05T10:46:23 -08:00"
		},
		{
			"drnumber": "01243773-60de-448e-ac09-224d291f03ff",
			"id": 20,
			"poid": 59,
			"created": "2016-12-20T09:15:00 -08:00",
			"updated": "2017-08-08T04:20:19 -08:00",
			"synced": "2014-10-14T12:45:19 -08:00"
		},
		{
			"drnumber": "650fed20-22a2-4ed3-afbf-8f5e1bcfedf0",
			"id": 21,
			"poid": 25,
			"created": "2017-02-09T03:01:20 -08:00",
			"updated": "2016-04-28T11:06:34 -08:00",
			"synced": "2017-07-17T04:34:22 -08:00"
		},
		{
			"drnumber": "4aaf480d-946f-4db2-b03c-83e0b3d9366f",
			"id": 22,
			"poid": 35,
			"created": "2017-07-08T10:52:39 -08:00",
			"updated": "2014-10-12T09:30:10 -08:00",
			"synced": "2014-08-30T09:45:22 -08:00"
		},
		{
			"drnumber": "8dfc6096-4740-4f74-8944-6fc81f3fd98b",
			"id": 23,
			"poid": 22,
			"created": "2016-10-04T09:55:09 -08:00",
			"updated": "2014-06-05T12:27:43 -08:00",
			"synced": "2014-11-19T02:22:39 -08:00"
		},
		{
			"drnumber": "e2f7e01a-d5f2-4a31-a560-aba2b8ec35e1",
			"id": 24,
			"poid": 94,
			"created": "2017-04-10T05:38:18 -08:00",
			"updated": "2014-01-23T08:33:34 -08:00",
			"synced": "2016-10-02T02:24:42 -08:00"
		},
		{
			"drnumber": "7a4722a1-6e12-431d-9740-9ed9559974d8",
			"id": 25,
			"poid": 97,
			"created": "2018-01-05T03:48:28 -08:00",
			"updated": "2016-09-02T02:57:14 -08:00",
			"synced": "2015-11-12T08:43:53 -08:00"
		},
		{
			"drnumber": "a7783f1e-b68e-4652-b3df-11aa27f2112d",
			"id": 26,
			"poid": 79,
			"created": "2015-12-04T09:30:41 -08:00",
			"updated": "2014-03-22T10:01:22 -08:00",
			"synced": "2014-12-22T10:07:02 -08:00"
		},
		{
			"drnumber": "9433e0bf-6f7c-40e5-8a0a-01483c31c499",
			"id": 27,
			"poid": 84,
			"created": "2017-09-26T02:17:44 -08:00",
			"updated": "2014-12-07T10:12:35 -08:00",
			"synced": "2014-09-19T12:48:38 -08:00"
		},
		{
			"drnumber": "0d6790ba-6705-4eda-bce5-94c823c5de7d",
			"id": 28,
			"poid": 14,
			"created": "2016-09-25T08:32:41 -08:00",
			"updated": "2014-03-21T01:14:21 -08:00",
			"synced": "2015-09-23T08:27:58 -08:00"
		},
		{
			"drnumber": "44a3ff2c-5b10-4b03-9f5f-3eb93d01d7cd",
			"id": 29,
			"poid": 2,
			"created": "2015-03-13T04:50:03 -08:00",
			"updated": "2017-04-08T11:56:23 -08:00",
			"synced": "2014-09-25T09:33:12 -08:00"
		},
		{
			"drnumber": "93ab74e1-c7a8-442c-983c-fb33944b7752",
			"id": 30,
			"poid": 34,
			"created": "2015-01-04T05:31:42 -08:00",
			"updated": "2017-12-28T07:42:54 -08:00",
			"synced": "2017-06-24T08:50:38 -08:00"
		},
		{
			"drnumber": "a3672051-10bc-4a5f-9b55-9b1a700e531a",
			"id": 31,
			"poid": 69,
			"created": "2015-10-27T05:51:16 -08:00",
			"updated": "2014-11-29T09:44:58 -08:00",
			"synced": "2016-11-21T12:45:53 -08:00"
		},
		{
			"drnumber": "e8e7ded0-3961-4999-8d74-b1d2d93579c5",
			"id": 32,
			"poid": 46,
			"created": "2015-12-17T10:27:29 -08:00",
			"updated": "2016-02-28T09:41:13 -08:00",
			"synced": "2015-07-12T01:32:43 -08:00"
		},
		{
			"drnumber": "8ff6befd-cf05-4491-87fc-95a681b30e0b",
			"id": 33,
			"poid": 34,
			"created": "2014-12-24T09:41:31 -08:00",
			"updated": "2014-04-14T03:59:06 -08:00",
			"synced": "2017-07-29T12:09:24 -08:00"
		},
		{
			"drnumber": "2ba95c1e-5b34-4613-9344-4578ddacf4c6",
			"id": 34,
			"poid": 89,
			"created": "2015-02-13T08:33:43 -08:00",
			"updated": "2015-04-16T02:16:18 -08:00",
			"synced": "2014-04-22T01:42:36 -08:00"
		},
		{
			"drnumber": "c4cf4cee-74aa-45a0-ad44-a2a5f9d5ee7e",
			"id": 35,
			"poid": 85,
			"created": "2014-08-14T11:05:48 -08:00",
			"updated": "2015-08-20T04:01:31 -08:00",
			"synced": "2016-08-19T03:58:23 -08:00"
		},
		{
			"drnumber": "b5d7c5d2-9c0f-4238-918f-a2d250f19870",
			"id": 36,
			"poid": 4,
			"created": "2014-10-25T10:59:39 -08:00",
			"updated": "2014-04-24T08:26:50 -08:00",
			"synced": "2015-08-09T05:56:09 -08:00"
		},
		{
			"drnumber": "e4b7de53-695c-4aef-890d-6c7d361126f0",
			"id": 37,
			"poid": 2,
			"created": "2017-01-23T05:15:27 -08:00",
			"updated": "2015-08-20T02:57:26 -08:00",
			"synced": "2014-11-07T01:38:06 -08:00"
		},
		{
			"drnumber": "338a2322-8c5a-4680-bf40-2cdd4ae405f7",
			"id": 38,
			"poid": 11,
			"created": "2015-03-10T11:57:50 -08:00",
			"updated": "2015-09-20T04:25:33 -08:00",
			"synced": "2014-12-23T09:07:13 -08:00"
		},
		{
			"drnumber": "b8edc7a5-7b6e-4006-8c95-6d94226f13a8",
			"id": 39,
			"poid": 3,
			"created": "2014-03-04T06:02:19 -08:00",
			"updated": "2016-11-18T05:07:18 -08:00",
			"synced": "2014-10-26T02:13:38 -08:00"
		},
		{
			"drnumber": "b4461c8d-b366-4764-9069-4a01149c8802",
			"id": 40,
			"poid": 90,
			"created": "2018-02-03T07:54:37 -08:00",
			"updated": "2016-09-15T02:03:27 -08:00",
			"synced": "2014-01-08T04:42:28 -08:00"
		},
		{
			"drnumber": "edb5ac28-308d-4202-8a16-6754920154b9",
			"id": 41,
			"poid": 38,
			"created": "2016-11-11T04:52:40 -08:00",
			"updated": "2015-07-17T04:49:38 -08:00",
			"synced": "2014-09-15T06:54:17 -08:00"
		},
		{
			"drnumber": "586d4716-46a4-470c-8f03-085fe303d478",
			"id": 42,
			"poid": 20,
			"created": "2015-08-11T11:11:22 -08:00",
			"updated": "2017-09-15T07:55:10 -08:00",
			"synced": "2016-07-20T02:08:18 -08:00"
		},
		{
			"drnumber": "93903a24-bcfc-4a4f-9791-42021f8e74aa",
			"id": 43,
			"poid": 13,
			"created": "2016-06-14T07:07:21 -08:00",
			"updated": "2017-09-17T02:01:50 -08:00",
			"synced": "2017-05-16T01:13:59 -08:00"
		},
		{
			"drnumber": "8f37f0ea-abf7-42cc-9fdb-1ca94c9a2998",
			"id": 44,
			"poid": 6,
			"created": "2016-08-05T06:08:30 -08:00",
			"updated": "2014-01-17T07:47:28 -08:00",
			"synced": "2015-04-30T03:20:26 -08:00"
		},
		{
			"drnumber": "ffce0a40-0dd4-4938-9084-a1d7412bc638",
			"id": 45,
			"poid": 74,
			"created": "2015-08-19T08:07:42 -08:00",
			"updated": "2014-02-23T05:09:34 -08:00",
			"synced": "2015-03-07T06:59:51 -08:00"
		},
		{
			"drnumber": "7206ce61-21df-4a65-9e81-9e84a04a11f1",
			"id": 46,
			"poid": 49,
			"created": "2015-02-25T06:06:19 -08:00",
			"updated": "2014-10-17T03:06:48 -08:00",
			"synced": "2015-07-04T03:24:59 -08:00"
		},
		{
			"drnumber": "37b69dc5-9818-464e-977a-7d5ff3ed000d",
			"id": 47,
			"poid": 19,
			"created": "2016-04-06T12:25:08 -08:00",
			"updated": "2016-03-03T06:12:53 -08:00",
			"synced": "2015-03-16T12:20:31 -08:00"
		},
		{
			"drnumber": "7e653f8b-37de-4eda-925e-ee11e2795634",
			"id": 48,
			"poid": 87,
			"created": "2017-12-26T04:38:52 -08:00",
			"updated": "2017-04-25T07:05:13 -08:00",
			"synced": "2015-08-31T06:24:11 -08:00"
		},
		{
			"drnumber": "d2c2370b-ee62-4421-a81e-c98e4dac45bd",
			"id": 49,
			"poid": 51,
			"created": "2018-03-08T07:39:20 -08:00",
			"updated": "2015-11-03T04:52:37 -08:00",
			"synced": "2014-05-21T04:25:21 -08:00"
		},
		{
			"drnumber": "af4e1480-63e4-4ef4-96d6-c68bb44d4320",
			"id": 50,
			"poid": 26,
			"created": "2014-10-02T05:48:06 -08:00",
			"updated": "2015-06-15T04:54:47 -08:00",
			"synced": "2014-11-02T03:45:30 -08:00"
		},
		{
			"drnumber": "b734e511-9578-4c52-8826-4c648fc85d69",
			"id": 51,
			"poid": 32,
			"created": "2017-02-09T08:45:23 -08:00",
			"updated": "2017-02-21T07:19:48 -08:00",
			"synced": "2014-05-04T11:57:47 -08:00"
		},
		{
			"drnumber": "229da093-c84c-4ae6-9c99-a16a2fb1d6ad",
			"id": 52,
			"poid": 24,
			"created": "2014-11-29T10:14:07 -08:00",
			"updated": "2014-10-17T07:52:28 -08:00",
			"synced": "2017-09-27T10:55:28 -08:00"
		},
		{
			"drnumber": "c0ab8842-c59f-4182-af91-ea52b63b27e3",
			"id": 53,
			"poid": 86,
			"created": "2017-04-25T07:34:38 -08:00",
			"updated": "2018-02-06T02:25:31 -08:00",
			"synced": "2015-07-21T01:35:27 -08:00"
		},
		{
			"drnumber": "832a99e6-8d53-4e1d-869e-b48d3895626d",
			"id": 54,
			"poid": 44,
			"created": "2014-05-14T05:48:31 -08:00",
			"updated": "2015-01-24T06:08:13 -08:00",
			"synced": "2018-03-04T05:53:50 -08:00"
		},
		{
			"drnumber": "e22f067d-259b-4f64-abe1-284556212d30",
			"id": 55,
			"poid": 15,
			"created": "2015-04-15T08:41:50 -08:00",
			"updated": "2014-08-05T07:27:16 -08:00",
			"synced": "2015-12-31T12:33:58 -08:00"
		},
		{
			"drnumber": "30364882-38ae-494d-bc20-43b76accdf9f",
			"id": 56,
			"poid": 30,
			"created": "2016-06-18T08:36:37 -08:00",
			"updated": "2016-12-11T02:16:37 -08:00",
			"synced": "2014-11-09T04:41:30 -08:00"
		},
		{
			"drnumber": "f5768f92-7860-4a4b-8cd7-f8aa70d85b13",
			"id": 57,
			"poid": 47,
			"created": "2014-12-22T11:54:07 -08:00",
			"updated": "2014-07-28T02:33:40 -08:00",
			"synced": "2016-06-12T07:52:29 -08:00"
		},
		{
			"drnumber": "c376a33f-52e7-40e4-9e88-3596467d3548",
			"id": 58,
			"poid": 28,
			"created": "2014-06-08T09:03:53 -08:00",
			"updated": "2016-11-01T06:05:28 -08:00",
			"synced": "2014-09-25T03:13:39 -08:00"
		},
		{
			"drnumber": "1cf2dd83-0ba3-4639-9826-8c1b9afcc804",
			"id": 59,
			"poid": 37,
			"created": "2016-11-28T01:34:18 -08:00",
			"updated": "2015-03-08T01:47:23 -08:00",
			"synced": "2016-11-01T08:23:01 -08:00"
		},
		{
			"drnumber": "244041ee-a764-4308-bd80-435501c48e6c",
			"id": 60,
			"poid": 93,
			"created": "2017-06-15T11:03:27 -08:00",
			"updated": "2016-06-05T04:02:05 -08:00",
			"synced": "2017-11-11T06:43:15 -08:00"
		},
		{
			"drnumber": "f847d3a9-e8dd-4cf3-91fe-ea00a67ff830",
			"id": 61,
			"poid": 69,
			"created": "2015-03-25T09:46:37 -08:00",
			"updated": "2016-07-13T03:10:59 -08:00",
			"synced": "2016-02-29T04:11:54 -08:00"
		},
		{
			"drnumber": "33f0ef56-91f5-4075-aa09-d9c80df21b38",
			"id": 62,
			"poid": 67,
			"created": "2017-03-27T02:43:33 -08:00",
			"updated": "2014-03-31T05:13:29 -08:00",
			"synced": "2015-12-27T11:52:20 -08:00"
		},
		{
			"drnumber": "6297ac2e-8b6e-455f-a61f-ec2a65765be4",
			"id": 63,
			"poid": 76,
			"created": "2017-07-05T12:09:45 -08:00",
			"updated": "2016-12-25T07:24:30 -08:00",
			"synced": "2016-07-04T09:23:12 -08:00"
		},
		{
			"drnumber": "4d972a1e-026a-4518-9039-66bc6c8bca38",
			"id": 64,
			"poid": 29,
			"created": "2015-01-07T07:05:30 -08:00",
			"updated": "2017-12-03T03:03:51 -08:00",
			"synced": "2016-05-14T10:58:34 -08:00"
		},
		{
			"drnumber": "44411e1b-8adc-44db-86ed-7991b0471736",
			"id": 65,
			"poid": 76,
			"created": "2015-10-22T11:28:42 -08:00",
			"updated": "2015-05-30T05:36:14 -08:00",
			"synced": "2017-10-05T08:29:26 -08:00"
		},
		{
			"drnumber": "a530a15d-131f-4520-91a1-35cafe1239f3",
			"id": 66,
			"poid": 54,
			"created": "2015-08-20T08:06:52 -08:00",
			"updated": "2018-01-23T08:06:34 -08:00",
			"synced": "2014-07-05T08:49:47 -08:00"
		},
		{
			"drnumber": "a42805fd-7b62-49b0-a304-f8854be86e89",
			"id": 67,
			"poid": 59,
			"created": "2015-12-06T03:05:38 -08:00",
			"updated": "2014-05-25T03:38:05 -08:00",
			"synced": "2015-09-09T05:14:01 -08:00"
		},
		{
			"drnumber": "9c415634-0ffe-4f4e-9236-ad8bf0350f4d",
			"id": 68,
			"poid": 83,
			"created": "2015-08-13T05:26:00 -08:00",
			"updated": "2017-01-19T01:32:55 -08:00",
			"synced": "2016-06-06T02:31:39 -08:00"
		},
		{
			"drnumber": "9dcb8a5f-2e2f-4d63-9c05-b2c5c38fca24",
			"id": 69,
			"poid": 66,
			"created": "2015-02-01T09:52:42 -08:00",
			"updated": "2015-07-14T01:25:04 -08:00",
			"synced": "2016-11-07T05:54:48 -08:00"
		},
		{
			"drnumber": "e4e0316d-1e05-40a4-8e9d-2caf379b45e7",
			"id": 70,
			"poid": 76,
			"created": "2017-07-31T05:01:48 -08:00",
			"updated": "2014-10-24T04:35:16 -08:00",
			"synced": "2017-08-27T03:48:29 -08:00"
		},
		{
			"drnumber": "bd70d428-2919-4526-b23c-46e2d5b719f1",
			"id": 71,
			"poid": 74,
			"created": "2015-05-26T03:04:13 -08:00",
			"updated": "2015-11-06T07:36:23 -08:00",
			"synced": "2014-12-22T03:10:55 -08:00"
		},
		{
			"drnumber": "255b256f-9795-4381-842f-9c0470371c39",
			"id": 72,
			"poid": 88,
			"created": "2015-06-16T07:27:06 -08:00",
			"updated": "2016-02-15T07:08:44 -08:00",
			"synced": "2016-06-21T06:16:31 -08:00"
		},
		{
			"drnumber": "d3956ebc-11c4-41a9-b6e8-b03737b471b9",
			"id": 73,
			"poid": 12,
			"created": "2015-01-06T10:13:42 -08:00",
			"updated": "2017-07-25T12:43:56 -08:00",
			"synced": "2016-12-17T11:53:09 -08:00"
		},
		{
			"drnumber": "fd2ad623-21ea-4846-9be9-4f0caaf823e5",
			"id": 74,
			"poid": 41,
			"created": "2015-07-23T12:05:51 -08:00",
			"updated": "2016-12-05T01:26:20 -08:00",
			"synced": "2016-11-07T01:32:49 -08:00"
		},
		{
			"drnumber": "1c0c7015-8e83-461e-b04a-4d1902dbe9a6",
			"id": 75,
			"poid": 18,
			"created": "2016-07-31T02:36:23 -08:00",
			"updated": "2018-01-11T01:18:30 -08:00",
			"synced": "2017-01-06T05:42:34 -08:00"
		},
		{
			"drnumber": "fa47f212-6bdb-4e0e-b751-1ea9851eaa20",
			"id": 76,
			"poid": 30,
			"created": "2015-12-07T02:55:42 -08:00",
			"updated": "2015-08-01T05:07:25 -08:00",
			"synced": "2017-03-27T02:45:27 -08:00"
		},
		{
			"drnumber": "606f84be-ac45-4dfd-9991-08c728be1b8c",
			"id": 77,
			"poid": 29,
			"created": "2014-04-07T11:29:53 -08:00",
			"updated": "2014-09-11T09:33:28 -08:00",
			"synced": "2015-10-12T06:49:29 -08:00"
		},
		{
			"drnumber": "b6e7aa78-fd16-4ff6-99f1-7d775372f72b",
			"id": 78,
			"poid": 97,
			"created": "2015-10-28T06:41:27 -08:00",
			"updated": "2017-07-06T11:50:57 -08:00",
			"synced": "2017-05-20T04:54:20 -08:00"
		},
		{
			"drnumber": "d9485158-a5b3-4d72-b6bd-a7cc97ed4ac1",
			"id": 79,
			"poid": 29,
			"created": "2015-05-03T01:02:55 -08:00",
			"updated": "2015-08-24T11:49:22 -08:00",
			"synced": "2017-04-22T10:48:58 -08:00"
		},
		{
			"drnumber": "75a6db1f-5ccb-4f6a-9551-bd66e6c9e16d",
			"id": 80,
			"poid": 68,
			"created": "2015-06-01T02:18:10 -08:00",
			"updated": "2014-12-04T09:55:57 -08:00",
			"synced": "2017-07-04T02:51:09 -08:00"
		},
		{
			"drnumber": "adbfc222-0d1c-4c56-9008-74135d7a0cf7",
			"id": 81,
			"poid": 33,
			"created": "2015-08-29T09:49:50 -08:00",
			"updated": "2016-08-25T02:49:18 -08:00",
			"synced": "2017-03-14T05:36:07 -08:00"
		},
		{
			"drnumber": "334482b2-35e4-4b79-935c-faf563335708",
			"id": 82,
			"poid": 90,
			"created": "2017-01-21T11:09:58 -08:00",
			"updated": "2016-12-03T01:45:45 -08:00",
			"synced": "2016-05-13T12:31:40 -08:00"
		},
		{
			"drnumber": "5cbfef16-398e-49df-be81-d884262aac62",
			"id": 83,
			"poid": 57,
			"created": "2017-09-07T09:12:21 -08:00",
			"updated": "2017-05-24T06:45:52 -08:00",
			"synced": "2014-09-30T12:14:14 -08:00"
		},
		{
			"drnumber": "cf225d59-fcf7-4620-8467-f98902e7e00c",
			"id": 84,
			"poid": 92,
			"created": "2016-03-05T10:17:11 -08:00",
			"updated": "2014-03-24T07:19:16 -08:00",
			"synced": "2016-05-13T06:57:51 -08:00"
		},
		{
			"drnumber": "10adff99-a83e-42ad-8bb6-14ebf9d7b6b9",
			"id": 85,
			"poid": 85,
			"created": "2016-01-24T03:56:05 -08:00",
			"updated": "2014-06-09T04:19:57 -08:00",
			"synced": "2017-08-11T08:04:06 -08:00"
		},
		{
			"drnumber": "84664f73-7589-4423-a3e3-3ebcfdae2131",
			"id": 86,
			"poid": 35,
			"created": "2017-03-09T07:46:24 -08:00",
			"updated": "2014-11-18T03:11:59 -08:00",
			"synced": "2014-08-04T09:10:14 -08:00"
		},
		{
			"drnumber": "4539b257-057c-4f97-8b34-ec5a97bef489",
			"id": 87,
			"poid": 37,
			"created": "2015-08-21T10:42:41 -08:00",
			"updated": "2016-10-01T04:12:07 -08:00",
			"synced": "2015-10-19T12:03:36 -08:00"
		},
		{
			"drnumber": "8f38466c-f6c2-45e1-9711-c21245635263",
			"id": 88,
			"poid": 4,
			"created": "2017-04-06T12:55:36 -08:00",
			"updated": "2014-09-11T01:05:37 -08:00",
			"synced": "2014-07-29T12:42:44 -08:00"
		},
		{
			"drnumber": "3fa5472d-4206-4e94-807a-254dfda87140",
			"id": 89,
			"poid": 78,
			"created": "2017-12-08T08:02:54 -08:00",
			"updated": "2016-12-06T05:04:18 -08:00",
			"synced": "2014-09-20T08:14:34 -08:00"
		},
		{
			"drnumber": "ec2ea914-e69d-421d-9f4f-91e8f20ae938",
			"id": 90,
			"poid": 28,
			"created": "2017-06-30T04:47:37 -08:00",
			"updated": "2015-10-21T02:28:34 -08:00",
			"synced": "2015-11-10T11:45:56 -08:00"
		},
		{
			"drnumber": "5646269d-94ce-4723-a221-ea1ad0279bed",
			"id": 91,
			"poid": 21,
			"created": "2015-07-09T11:35:26 -08:00",
			"updated": "2017-07-17T08:55:08 -08:00",
			"synced": "2017-09-07T04:04:14 -08:00"
		},
		{
			"drnumber": "5d376a7f-2637-4476-b835-bb9e7e7a961d",
			"id": 92,
			"poid": 47,
			"created": "2016-06-22T04:01:30 -08:00",
			"updated": "2016-09-16T05:41:46 -08:00",
			"synced": "2014-12-27T05:20:24 -08:00"
		},
		{
			"drnumber": "e0298df2-a9bd-465d-800d-9508a2cba8e1",
			"id": 93,
			"poid": 59,
			"created": "2015-05-29T09:27:24 -08:00",
			"updated": "2014-12-11T11:39:00 -08:00",
			"synced": "2014-03-24T09:51:18 -08:00"
		},
		{
			"drnumber": "0b4e4422-55b6-48c3-8b1e-22ebbc5c6bf2",
			"id": 94,
			"poid": 90,
			"created": "2014-03-22T11:58:30 -08:00",
			"updated": "2017-12-09T01:03:57 -08:00",
			"synced": "2016-10-26T09:37:38 -08:00"
		},
		{
			"drnumber": "c0e3a8ac-2a41-412f-a8c5-c2e424718397",
			"id": 95,
			"poid": 74,
			"created": "2016-11-14T03:06:36 -08:00",
			"updated": "2015-02-10T10:31:23 -08:00",
			"synced": "2015-11-21T08:31:26 -08:00"
		},
		{
			"drnumber": "0ea78c3c-a642-4ada-b798-937b96c17fd3",
			"id": 96,
			"poid": 83,
			"created": "2017-10-27T05:04:54 -08:00",
			"updated": "2016-02-05T06:32:39 -08:00",
			"synced": "2015-03-13T03:26:47 -08:00"
		},
		{
			"drnumber": "afc4365f-2029-44c3-ad62-3e61b4c215a1",
			"id": 97,
			"poid": 79,
			"created": "2014-06-29T06:40:54 -08:00",
			"updated": "2015-11-10T09:27:09 -08:00",
			"synced": "2017-06-06T10:31:45 -08:00"
		},
		{
			"drnumber": "f46560d2-f62f-4493-9526-7daef1e24035",
			"id": 98,
			"poid": 72,
			"created": "2014-08-01T06:07:14 -08:00",
			"updated": "2016-05-31T07:56:39 -08:00",
			"synced": "2015-03-26T07:38:55 -08:00"
		},
		{
			"drnumber": "c1c8c29c-6222-4d3e-beb0-dbb124d2fdeb",
			"id": 99,
			"poid": 53,
			"created": "2015-08-01T05:52:23 -08:00",
			"updated": "2017-02-21T11:19:08 -08:00",
			"synced": "2017-07-31T07:50:52 -08:00"
		}
	]
}